LICENSE
pydantic2avro/__init__.py
pydantic2avro/enums.py
pydantic2avro/exceptions.py
pydantic2avro/schema_component_types.py
pydantic2avro/schema_maker.py
pydantic2avro/schema_options.py
pydantic2avro-0.4.1.dist-info/LICENSE
pydantic2avro-0.4.1.dist-info/METADATA
pydantic2avro-0.4.1.dist-info/WHEEL
pydantic2avro-0.4.1.dist-info/RECORD
