Metadata-Version: 2.1
Name: pydantic2avro
Version: 0.4.1
Summary: Generate Apache Avro schemas for Pydantic data models.
Home-page: https://github.com/Happy-Kunal/pydantic2avro
License: MIT
Keywords: pydantic,avro,kafka,messaging,schema,serialization,python
Author: Kunal Sharma
Author-email: happykunal@proton.me
Requires-Python: >=3.11,<4.0
Classifier: License :: OSI Approved :: MIT License
Classifier: Programming Language :: Python :: 3
Classifier: Programming Language :: Python :: 3.11
Classifier: Programming Language :: Python :: 3.12
Requires-Dist: pydantic[email] (>=2.6.3,<3.0.0)
Project-URL: Repository, https://github.com/Happy-Kunal/pydantic2avro
